k8secrets/__init__.py
k8secrets/__main__.py
k8secrets/generator.py
k8secrets/py.typed
k8secrets/secrets.py
k8secrets-1.0.0.dist-info/entry_points.txt
k8secrets-1.0.0.dist-info/LICENSE
k8secrets-1.0.0.dist-info/WHEEL
k8secrets-1.0.0.dist-info/METADATA
k8secrets-1.0.0.dist-info/RECORD
